pyqiwi/__init__.py
pyqiwi/__version__.py
pyqiwi/apihelper.py
pyqiwi/exceptions.py
pyqiwi/types.py
pyqiwi/util.py
qiwipy-2.1.6.dist-info/AUTHORS.rst
qiwipy-2.1.6.dist-info/LICENSE
qiwipy-2.1.6.dist-info/METADATA
qiwipy-2.1.6.dist-info/WHEEL
qiwipy-2.1.6.dist-info/top_level.txt
qiwipy-2.1.6.dist-info/RECORD
