Metadata-Version: 2.1
Name: qiwipy
Version: 2.1.6
Summary: Python Qiwi API Wrapper
Home-page: https://github.com/mostm/pyqiwi
Author: Levent Duivel
Author-email: mostm@endcape.ru
License: MIT
Keywords: pyqiwi
Platform: UNKNOWN
Classifier: Development Status :: 5 - Production/Stable
Classifier: Intended Audience :: Developers
Classifier: License :: OSI Approved :: MIT License
Classifier: Natural Language :: English
Classifier: Programming Language :: Python :: 3
Classifier: Programming Language :: Python :: 3.5
Classifier: Programming Language :: Python :: 3.6
Requires-Dist: six
Requires-Dist: requests (<3,>=2.15)
Requires-Dist: parse (<2,>=1.8)
Requires-Dist: python-dateutil (<3,>=2.7)
